elias/__init__.py
elias/config.py
elias/data/__init__.py
elias/data/combined.py
elias/data/loader.py
elias/data/sampling.py
elias/data/stop_criterion.py
elias/folder/__init__.py
elias/folder/analysis.py
elias/folder/data.py
elias/folder/folder.py
elias/folder/model.py
elias/folder/run.py
elias/manager/__init__.py
elias/manager/analysis.py
elias/manager/artifact.py
elias/manager/buffered.py
elias/manager/data.py
elias/manager/model.py
elias/manager/run.py
elias/util/__init__.py
elias/util/batch.py
elias/util/dataclass.py
elias/util/fs.py
elias/util/io.py
elias/util/logger_bundle.py
elias/util/random.py
elias/util/range.py
elias/util/timing.py
elias/util/typing.py
elias/util/version.py
elias/util/wandb_images.py
elias-0.4.19.dist-info/licenses/LICENSE
elias-0.4.19.dist-info/METADATA
elias-0.4.19.dist-info/WHEEL
elias-0.4.19.dist-info/top_level.txt
elias-0.4.19.dist-info/RECORD
