Metadata-Version: 2.4
Name: elias
Version: 0.4.19
Summary: ELIAS experiment library for facilitating machine learning projects
Home-page: https://github.com/tobias-kirschstein/elias
Author: Tobias Kirschstein
Author-email: tobias.kirschstein@gmail.com
Classifier: Programming Language :: Python :: 3
Classifier: License :: OSI Approved :: MIT License
Classifier: Operating System :: OS Independent
Requires-Python: >=3.6
License-File: LICENSE
Requires-Dist: dacite<=1.7.0
Requires-Dist: pyyaml>=5.4.1
Requires-Dist: numpy>=1.20.2
Requires-Dist: testfixtures>=6.18.0
Requires-Dist: matplotlib>=3.4.2
Requires-Dist: silberstral>=0.2.3
Requires-Dist: opencv-python
Requires-Dist: imageio
Requires-Dist: requests
Requires-Dist: tabulate
Requires-Dist: pillow-avif-plugin<=1.4.6
Dynamic: license-file
